config_sci
